server.py
bachai_facebook-1.0.3.dist-info/METADATA
bachai_facebook-1.0.3.dist-info/WHEEL
bachai_facebook-1.0.3.dist-info/entry_points.txt
bachai_facebook-1.0.3.dist-info/top_level.txt
bachai_facebook-1.0.3.dist-info/RECORD
