Metadata-Version: 2.4
Name: bachai-facebook
Version: 1.0.3
Summary: Facebook Scraper MCP Server - 提供8个Facebook搜索工具的Model Context Protocol服务器
Home-page: https://github.com/BACH-AI-Tools/facebook
Author: BACH Studio
Author-email: BACH Studio <contact@bachstudio.com>
License: MIT
Project-URL: Homepage, https://github.com/BACH-AI-Tools/facebook
Classifier: Programming Language :: Python :: 3
Classifier: License :: OSI Approved :: MIT License
Classifier: Operating System :: OS Independent
Requires-Python: >=3.7
Requires-Dist: mcp>=0.9.0
Requires-Dist: httpx>=0.27.0
Dynamic: author
Dynamic: home-page
Dynamic: requires-python
